pytrain/__init__.py
pytrain/_version.py
pytrain/atc/__init__.py
pytrain/atc/block.py
pytrain/cli/__init__.py
pytrain/cli/acc.py
pytrain/cli/amc2.py
pytrain/cli/asc2.py
pytrain/cli/bpc2.py
pytrain/cli/dialogs.py
pytrain/cli/echo.py
pytrain/cli/effects.py
pytrain/cli/engine.py
pytrain/cli/halt.py
pytrain/cli/lighting.py
pytrain/cli/make_base.py
pytrain/cli/make_gui.py
pytrain/cli/make_service.py
pytrain/cli/piconfig.py
pytrain/cli/pytrain.py
pytrain/cli/route.py
pytrain/cli/sounds.py
pytrain/cli/switch.py
pytrain/comm/__init__.py
pytrain/comm/comm_buffer.py
pytrain/comm/command_listener.py
pytrain/comm/enqueue_proxy_requests.py
pytrain/comm/serial_reader.py
pytrain/db/__init__.py
pytrain/db/accessory_state.py
pytrain/db/base_state.py
pytrain/db/block_state.py
pytrain/db/client_state_listener.py
pytrain/db/comp_data.py
pytrain/db/component_state.py
pytrain/db/component_state_store.py
pytrain/db/components.py
pytrain/db/engine_state.py
pytrain/db/irda_state.py
pytrain/db/prod_info.py
pytrain/db/startup_state.py
pytrain/db/state_watcher.py
pytrain/db/sync_state.py
pytrain/db/watchable.py
pytrain/gpio/__init__.py
pytrain/gpio/base_watcher.py
pytrain/gpio/controller.py
pytrain/gpio/crane_car.py
pytrain/gpio/culvert_loader.py
pytrain/gpio/engine_controller.py
pytrain/gpio/engine_status.py
pytrain/gpio/gantry_crane.py
pytrain/gpio/gpio_device.py
pytrain/gpio/gpio_handler.py
pytrain/gpio/keypad.py
pytrain/gpio/launch_pad.py
pytrain/gpio/launch_status.py
pytrain/gpio/power_district.py
pytrain/gpio/power_watcher.py
pytrain/gpio/py_rotary_encoder.py
pytrain/gpio/route.py
pytrain/gpio/smoke_fluid_loader.py
pytrain/gpio/state_source.py
pytrain/gpio/switch.py
pytrain/gpio/sys_admin.py
pytrain/gpio/i2c/__init__.py
pytrain/gpio/i2c/ads_1x15.py
pytrain/gpio/i2c/analog_handler_i2c.py
pytrain/gpio/i2c/button_i2c.py
pytrain/gpio/i2c/i2c.py
pytrain/gpio/i2c/i2c_device.py
pytrain/gpio/i2c/lcd.py
pytrain/gpio/i2c/led_i2c.py
pytrain/gpio/i2c/mcp23017.py
pytrain/gpio/i2c/oled.py
pytrain_ogr-1.6.11.dist-info/licenses/AUTHORS
pytrain_ogr-1.6.11.dist-info/licenses/LICENSE
pytrain_ogr-1.6.11.dist-info/METADATA
pytrain_ogr-1.6.11.dist-info/WHEEL
pytrain_ogr-1.6.11.dist-info/entry_points.txt
pytrain_ogr-1.6.11.dist-info/top_level.txt
pytrain_ogr-1.6.11.dist-info/RECORD
