Metadata-Version: 2.4
Name: pytrain-ogr
Version: 1.6.11
Summary: Control Lionel TMCC/Legacy engines, switches, and accesseries from a Raspberry Pi
Author-email: Dave Swindell <pytraininfo@gmail.com>
License:                    GNU LESSER GENERAL PUBLIC LICENSE
Project-URL: Homepage, https://github.com/cdswindell/PyLegacy
Project-URL: Source, https://github.com/cdswindell/PyLegacy
Project-URL: Issues, https://github.com/cdswindell/PyLegacy/issues
Keywords: automation,interactive,control,control panel,legacy,lionel,model railroad,o-gauge,raspberry pi,tmcc,trains
Classifier: Development Status :: 5 - Production/Stable
Classifier: Environment :: Console
Classifier: Intended Audience :: Developers
Classifier: Intended Audience :: Other Audience
Classifier: License :: OSI Approved :: GNU Lesser General Public License v3 (LGPLv3)
Classifier: Natural Language :: English
Classifier: Operating System :: POSIX :: Linux
Classifier: Operating System :: MacOS :: MacOS X
Classifier: Programming Language :: Python :: 3
Classifier: Programming Language :: Python :: 3.11
Classifier: Programming Language :: Python :: 3.12
Classifier: Programming Language :: Python :: 3.13
Requires-Python: >=3.10
License-File: LICENSE
License-File: AUTHORS
Requires-Dist: RPLCD>=1.4.0
Requires-Dist: colorzero>=2.0
Requires-Dist: gpiozero>=2.0.1
Requires-Dist: guizero>=1.6.0
Requires-Dist: luma.oled>=3.14.0
Requires-Dist: psutil>=5.9.8
Requires-Dist: python-dotenv>=1.2.1
Requires-Dist: pyserial>=3.5
Requires-Dist: range-key-dict>=1.1
Requires-Dist: requests>=2.32.5
Requires-Dist: rpi-lgpio>=0.6; platform_system == "Linux"
Requires-Dist: setuptools>=80.9.0
Requires-Dist: setuptools_scm>=9.2.2
Requires-Dist: smbus2>=0.6.0
Requires-Dist: zeroconf>=0.148.0
Requires-Dist: spidev>=3.8.0; platform_system == "Linux"
Dynamic: license-file
